{"symbols":{"CheckmarkPipe":{"hasNamespace":false,"type":0,"moduleName":"checkmark.pipe","relativePath":"app/core/checkmark/checkmark.pipe"},"PhoneCatAppComponent":{"hasNamespace":false,"type":0,"moduleName":"app.component","relativePath":"app/app.component"},"Phone":{"hasNamespace":false,"type":0,"moduleName":"phone.service","relativePath":"app/core/phone/phone.service"},"PhoneData":{"hasNamespace":false,"type":1,"moduleName":"phone.service","relativePath":"app/core/phone/phone.service"},"PhoneDetailController":{"hasNamespace":false,"type":0,"moduleName":"phone-detail.component","relativePath":"app/phone-detail/phone-detail.component"},"PhoneDetailComponent":{"hasNamespace":false,"type":0,"moduleName":"phone-detail.component","relativePath":"app/phone-detail/phone-detail.component"},"PhoneListController":{"hasNamespace":false,"type":0,"moduleName":"phone-list.component","relativePath":"app/phone-list/phone-list.component"},"PhoneListComponent":{"hasNamespace":false,"type":0,"moduleName":"phone-list.component","relativePath":"app/phone-list/phone-list.component"},"MenuNgModule":{"hasNamespace":false,"type":0,"moduleName":"app.module.ng1","relativePath":"app/app.module.ng1"},"Ng1Ng2UrlHandlingStrategy":{"hasNamespace":false,"type":0,"moduleName":"app.module","relativePath":"app/app.module"},"RootComponent":{"hasNamespace":false,"type":0,"moduleName":"app.module","relativePath":"app/app.module"},"AppModule":{"hasNamespace":false,"type":0,"moduleName":"app.module","relativePath":"app/app.module"}},"files":{"app/core/phone/phone.service.ts":"2016-11-21T18:46:09.000Z","app/app.config.ts":"2016-11-21T18:44:40.000Z","app/phone-list/phone-list.component.ts":"2016-11-21T18:46:54.000Z","app/phone-detail/phone-detail.component.ts":"2016-11-21T18:46:46.000Z","app/app.module.ng1.ts":"2016-11-22T19:25:11.000Z","app/app.module.ts":"2016-11-22T19:40:31.000Z","app/main.ts":"2016-11-22T19:41:08.000Z","app/core/checkmark/checkmark.filter.ts":"2016-11-21T19:29:56.000Z","app/adapter.ts":"2016-11-16T19:13:28.000Z","app/app.component.ts":"2016-11-16T23:23:44.000Z","app/core/core.module.ts":"2016-11-21T19:28:51.000Z","app/phone-detail/phone-detail.module.ts":"2016-11-19T02:04:39.000Z","app/phone-list/phone-list.module.ts":"2016-11-19T02:05:32.000Z","app/core/phone/phone.module.ts":"2016-11-19T02:03:20.000Z","app/core/checkmark/checkmark.pipe.ts":"2016-11-17T19:18:21.000Z"}}